xdat/LICENSE
xdat/VERSION
xdat/__init__.py
xdat/excel_xml_reader.py
xdat/x1d.py
xdat/xagg.py
xdat/xanvil.py
xdat/xbaikal.py
xdat/xcache.py
xdat/xcalc.py
xdat/xchecks.py
xdat/xcolor.py
xdat/xcv.py
xdat/xdata.py
xdat/xeda.py
xdat/xexamine_data.py
xdat/xfactors.py
xdat/xincludes.py
xdat/xkeras.py
xdat/xmodels.py
xdat/xmunge.py
xdat/xnp.py
xdat/xparallel.py
xdat/xpd.py
xdat/xplots.py
xdat/xplt.py
xdat/xpptx.py
xdat/xproblem.py
xdat/xsettings.py
xdat/xsklearn.py
xdat/xstan.py
xdat/xstats.py
xdat/xtext.py
xdat/xtf.py
xdat/xtree.py
xdat/xutils.py
xdat/xweights.py
xdat/media/default_theme.pptx
xdat/tests/__init__.py
xdat/tests/test_xagg.py
xdat/tests/test_xnp.py
xdat/tests/test_xpd.py
xdat/tests/test_xplots.py
xdat/tests/test_xstats.py
xdat/utilities/__init__.py
xdat/utilities/diagnose-gpu.py
xdat/utilities/try_excel_open.py
xdat-0.1.298.dist-info/licenses/LICENSE
xdat-0.1.298.dist-info/METADATA
xdat-0.1.298.dist-info/WHEEL
xdat-0.1.298.dist-info/top_level.txt
xdat-0.1.298.dist-info/RECORD
